git_groomer/__init__.py
git_groomer/base/__init__.py
git_groomer/base/client.py
git_groomer/base/exceptions.py
git_groomer/base/objects.py
git_groomer/gitlab/__init__.py
git_groomer/gitlab/client.py
git_groomer/gitlab/objects.py
tests/base/__init__.py
tests/base/conftest.py
tests/base/test_client.py
tests/base/test_objects.py
tests/gitlab/__init__.py
tests/gitlab/conftest.py
tests/gitlab/test_client.py
tests/gitlab/test_objects.py
git_groomer-0.0.0a1.dist-info/LICENSE
git_groomer-0.0.0a1.dist-info/METADATA
git_groomer-0.0.0a1.dist-info/WHEEL
git_groomer-0.0.0a1.dist-info/top_level.txt
git_groomer-0.0.0a1.dist-info/RECORD
