Metadata-Version: 2.1
Name: git-groomer
Version: 0.0.0a1
Summary: Tool to take good care of your git repository.
Home-page: https://github.com/JavierLuna/git-groomer
Author: Javier Luna Molina
Author-email: javierlunamolina@gmail.com
License: UNKNOWN
Keywords: git repository gitlab git-grooming grooming groom branch commit repo
Platform: UNKNOWN
Classifier: Development Status :: 3 - Alpha
Classifier: Intended Audience :: Developers
Classifier: Topic :: Software Development :: Libraries :: Python Modules
Classifier: License :: OSI Approved :: GNU General Public License v3 (GPLv3)
Classifier: Natural Language :: English
Classifier: Programming Language :: Python :: 3.6
Classifier: Programming Language :: Python :: 3.7
Requires-Dist: requests
Requires-Dist: maya
